elementary/.prettierignore
elementary/__init__.py
elementary/cli/__init__.py
elementary/cli/cli.py
elementary/cli/logo.py
elementary/cli/upgrade.py
elementary/clients/__init__.py
elementary/clients/api/__init__.py
elementary/clients/api/api_client.py
elementary/clients/azure/__init__.py
elementary/clients/azure/client.py
elementary/clients/dbt/__init__.py
elementary/clients/dbt/api_dbt_runner.py
elementary/clients/dbt/base_dbt_runner.py
elementary/clients/dbt/command_line_dbt_runner.py
elementary/clients/dbt/dbt_fusion_runner.py
elementary/clients/dbt/dbt_log.py
elementary/clients/dbt/factory.py
elementary/clients/dbt/subprocess_dbt_runner.py
elementary/clients/fetcher/__init__.py
elementary/clients/fetcher/fetcher.py
elementary/clients/gcs/__init__.py
elementary/clients/gcs/client.py
elementary/clients/s3/__init__.py
elementary/clients/s3/client.py
elementary/clients/slack/__init__.py
elementary/clients/slack/client.py
elementary/clients/slack/schema.py
elementary/clients/slack/slack_message_builder.py
elementary/config/__init__.py
elementary/config/config.py
elementary/exceptions/__init__.py
elementary/exceptions/exceptions.py
elementary/messages/README.md
elementary/messages/__init__.py
elementary/messages/block_builders.py
elementary/messages/blocks.py
elementary/messages/formats/__init__.py
elementary/messages/formats/adaptive_cards.py
elementary/messages/formats/block_kit.py
elementary/messages/formats/html.py
elementary/messages/formats/markdown.py
elementary/messages/formats/text.py
elementary/messages/formats/unicode.py
elementary/messages/message_body.py
elementary/messages/messaging_integrations/README.md
elementary/messages/messaging_integrations/__init__.py
elementary/messages/messaging_integrations/base_messaging_integration.py
elementary/messages/messaging_integrations/empty_message_context.py
elementary/messages/messaging_integrations/exceptions.py
elementary/messages/messaging_integrations/file_system.py
elementary_data-0.20.1.dist-info/METADATA
elementary_data-0.20.1.dist-info/WHEEL
elementary_data-0.20.1.dist-info/entry_points.txt
elementary_data-0.20.1.dist-info/licenses/LICENSE
elementary_data-0.20.1.dist-info/RECORD
