Metadata-Version: 2.4
Name: elementary-data
Version: 0.20.1
Summary: Data monitoring and lineage
License: Apache-2.0
License-File: LICENSE
Keywords: data,lineage,data lineage,data warehouse,DWH,observability,data monitoring,data observability,Snowflake,BigQuery,Redshift,data reliability,analytics engineering
Author: Elementary
Requires-Python: >=3.9,<3.13
Classifier: License :: OSI Approved :: Apache Software License
Classifier: Programming Language :: Python :: 3
Classifier: Programming Language :: Python :: 3.9
Classifier: Programming Language :: Python :: 3.10
Classifier: Programming Language :: Python :: 3.11
Classifier: Programming Language :: Python :: 3.12
Provides-Extra: all
Provides-Extra: athena
Provides-Extra: bigquery
Provides-Extra: clickhouse
Provides-Extra: databricks
Provides-Extra: postgres
Provides-Extra: redshift
Provides-Extra: snowflake
Provides-Extra: spark
Provides-Extra: trino
Requires-Dist: alive-progress (<=2.3.1)
Requires-Dist: azure-storage-blob (>=12.11.0)
Requires-Dist: beautifulsoup4 (<5.0.0)
Requires-Dist: boto3 (<2.0.0)
Requires-Dist: click (>=7.0,<9.0)
Requires-Dist: dbt-athena-community (>=1.6.3,<2.0.0) ; extra == "athena" or extra == "all"
Requires-Dist: dbt-bigquery (>=0.20,<2.0.0) ; extra == "bigquery" or extra == "all"
Requires-Dist: dbt-clickhouse (>=0.20,<2.0.0) ; extra == "clickhouse" or extra == "all"
Requires-Dist: dbt-core (>=0.20,<2.0.0)
Requires-Dist: dbt-databricks (>=0.20,<2.0.0) ; extra == "databricks" or extra == "all"
Requires-Dist: dbt-postgres (>=0.20,<2.0.0) ; extra == "postgres" or extra == "all"
Requires-Dist: dbt-redshift (>=0.20,<2.0.0) ; extra == "redshift" or extra == "all"
Requires-Dist: dbt-snowflake (>=0.20,<2.0.0) ; extra == "snowflake" or extra == "all"
Requires-Dist: dbt-spark (>=0.20,<2.0.0) ; extra == "spark" or extra == "all"
Requires-Dist: dbt-trino (>=1.5.0,<2.0.0) ; extra == "trino" or extra == "all"
Requires-Dist: google-cloud-storage (<3.0.0)
Requires-Dist: networkx (>=2.3,<3)
Requires-Dist: numpy (<2.0.0)
Requires-Dist: packaging (>=20.9)
Requires-Dist: posthog (<3.0.0)
Requires-Dist: pydantic (<3.0)
Requires-Dist: pymsteams (>=0.2.2,<1.0.0)
Requires-Dist: pytz (>=2025.1)
Requires-Dist: ratelimit
Requires-Dist: requests (>=2.28.1,<3.0.0)
Requires-Dist: ruamel.yaml (<1.0.0)
Requires-Dist: slack-sdk (>=3.20.1,<4.0.0)
Requires-Dist: tabulate (>=0.9.0)
Project-URL: Documentation, https://docs.elementary-data.com
Project-URL: Homepage, https://www.elementary-data.com
Project-URL: Repository, https://github.com/elementary-data/elementary
